gen_message_queue/__init__.py
gen_message_queue/py.typed
gen_message_queue/conf/gen_message_queue.cfg
gen_message_queue/conf/gen_message_queue.logo
gen_message_queue/conf/gen_message_queue_util.cfg
gen_message_queue/conf/project.yaml
gen_message_queue/conf/template/posix/mq_posix.template
gen_message_queue/conf/template/posix/mq_posix_close.template
gen_message_queue/conf/template/posix/mq_posix_fatal_error.template
gen_message_queue/conf/template/posix/mq_posix_open.template
gen_message_queue/conf/template/posix/mq_posix_open_mode.template
gen_message_queue/conf/template/posix/mq_posix_receive.template
gen_message_queue/conf/template/posix/mq_posix_send.template
gen_message_queue/conf/template/posix/mq_posix_unlink.template
gen_message_queue/conf/template/sysv/mq_sysv.template
gen_message_queue/conf/template/sysv/mq_sysv_control.template
gen_message_queue/conf/template/sysv/mq_sysv_file_to_key.template
gen_message_queue/conf/template/sysv/mq_sysv_get_buffer.template
gen_message_queue/conf/template/sysv/mq_sysv_get_buffer_type.template
gen_message_queue/conf/template/sysv/mq_sysv_key_to_id.template
gen_message_queue/conf/template/sysv/mq_sysv_receive.template
gen_message_queue/conf/template/sysv/mq_sysv_send.template
gen_message_queue/conf/template/sysv/mq_sysv_set_buffer.template
gen_message_queue/conf/template/sysv/mq_sysv_set_buffer_type.template
gen_message_queue/log/gen_message_queue.log
gen_message_queue/pro/__init__.py
gen_message_queue/pro/read_template.py
gen_message_queue/pro/write_template.py
usr/local/bin/gen_message_queue_run.py
gen_message_queue-1.1.5.dist-info/LICENSE
gen_message_queue-1.1.5.dist-info/METADATA
gen_message_queue-1.1.5.dist-info/WHEEL
gen_message_queue-1.1.5.dist-info/top_level.txt
gen_message_queue-1.1.5.dist-info/RECORD
